llama_index/tools/salesforce/__init__.py
llama_index/tools/salesforce/base.py
llama_index_tools_salesforce-0.4.1.dist-info/METADATA
llama_index_tools_salesforce-0.4.1.dist-info/WHEEL
llama_index_tools_salesforce-0.4.1.dist-info/licenses/LICENSE
llama_index_tools_salesforce-0.4.1.dist-info/RECORD
