Metadata-Version: 2.4
Name: llama-index-tools-salesforce
Version: 0.4.1
Summary: llama-index tools salesforce integration
Author-email: Your Name <you@example.com>
Maintainer: chrispangg
License-Expression: MIT
License-File: LICENSE
Keywords: salesforce
Requires-Python: <4.0,>=3.9
Requires-Dist: llama-index-core<0.15,>=0.13.0
Requires-Dist: simple-salesforce<2,>=1.12.5
